fastofreader/__init__.py
fastofreader/__init__.pyi
fastofreader/boundary.py
fastofreader/core.c
fastofreader/core.cpython-311-x86_64-linux-gnu.so
fastofreader/core.pyx
fastofreader/py.typed
fastofreader-0.2.0.dist-info/METADATA
fastofreader-0.2.0.dist-info/WHEEL
fastofreader-0.2.0.dist-info/top_level.txt
fastofreader-0.2.0.dist-info/RECORD
fastofreader-0.2.0.dist-info/licenses/LICENSE
